MANIFEST.in
README.rst
setup.cfg
setup.py
bin/pdf2zip
pdf2zip/__init__.py
pdf2zip.egg-info/PKG-INFO
pdf2zip.egg-info/SOURCES.txt
pdf2zip.egg-info/dependency_links.txt
pdf2zip.egg-info/entry_points.txt
pdf2zip.egg-info/not-zip-safe
pdf2zip.egg-info/top_level.txt