Metadata-Version: 1.0
Name: pdf2zip
Version: 1.0
Summary: pdf conversion utility
Home-page: http://github.com/jmoiron/pdf2zip
Author: Jason Moiron
Author-email: jmoiron@jmoiron.net
License: MIT
Keywords: pdf to jpeg conversion
Platform: UNKNOWN
Classifier: Development Status :: 5 - Production/Stable
Classifier: Environment :: Console
Classifier: Intended Audience :: End Users/Desktop
Classifier: License :: OSI Approved :: MIT License
Classifier: Operating System :: POSIX
